mercury_muscle/__init__.py
mercury_muscle/rule.py
mercury_muscle/score.py
mercury_muscle/utils.py
mercury_muscle-0.1.2.dist-info/LICENSE
mercury_muscle-0.1.2.dist-info/METADATA
mercury_muscle-0.1.2.dist-info/WHEEL
mercury_muscle-0.1.2.dist-info/RECORD
